{
    "$schema": "vscode://schemas/color-theme",
    "name": "Default Dark Modern (OLED Black) [White]",
    "include": "./dark_modern_oled.json",
    "colors": {
        "activityBarBadge.background": "#fff",
        "activityBar.foreground": "#fff",
        "activityBar.activeBorder": "#fff",
        "editorLineNumber.activeForeground": "#fff",
        "notificationCenterHeader.background": "#fff",
        "panelTitle.activeBorder": "#fff",
        "panelTitle.activeForeground": "#fff",
        "progressBar.background": "#fff",
        "scrollbarSlider.activeBackground": "#fff",
        "settings.modifiedItemIndicator": "#fff",
        "checkbox.foreground": "#fff",
        "statusBar.border": "#fff",
        "statusBar.foreground": "#fff",
        "statusBarItem.remoteForeground": "#fff",
        "tab.activeForeground": "#fff",
        "badge.background": "#fff",
        "badge.foreground": "#000",
        "button.background": "#fff",
        "button.foreground": "#000",
        "button.hoverBackground": "#ffffffe6",
        "editorGutter.modifiedBackground": "#fff",
        "focusBorder": "#fff",
        "inputOption.activeBackground": "#ffffff82",
        "inputOption.activeBorder": "#fff",
        "statusBar.focusBorder": "#fff",
        "statusBarItem.focusBorder": "#fff",
        "tab.activeBorderTop": "#fff",
        "terminal.tab.activeBorder": "#fff",
        "welcomePage.progress.foreground": "#fff",
    }
}
